{"_comment" : "Created by ianb on 16\/12\/2014 11:02:48 using v2.3","import_id" : "QIAAN104-1","title" : "Has the number of ACS admissions increased over time?","analysis_commentary" : "<P>ACS admission can be defined on the basis of the most important (primary) diagnosis or as one of the many possible secondary diagnoses. Between 2001\/02 and 2013\/14 the annual number of emergency admissions for ACS conditions increased by 48%, rising from 704,153 to 1,039,242 – an increase of 335,089. Over the same time period emergency admissions for non-ACS conditions increased by only 34%, meaning that the proportion of all emergency admissions that were ACS increased from 18% in 2001\/02 to 20% in 2013\/14.<\/P>","data_download_url" : {"url" : "","title" : ""},"data_source" : "Health & Social Care Information Centre, Hospital Episode Statistics (Copyright 2013, Re-used with the permission of the Health & Social Care Information Centre. All rights reserved)"}