{"_comment" : "Created by rreed on 20\/02\/2017 12:58:41 using v2.7","import_id" : "QIAAN99-8","title" : "How has the number of ambulance staff changed over time?","analysis_commentary" : "<P>The number of ambulance staff in England has been above 17,000 since October 2009 and numbers remained relatively steady until Septemer 2015. Since then there has been a noticable rise in the number of ambulance staff to 19,406 as of October 2016.<br><br>Updated January 2017.<\/P>","data_download_url" : {"url" : "","title" : ""},"data_source" : "<a href=\"http:\/\/content.digital.nhs.uk\/article\/2021\/Website-Search?q=workforce+statistics&go=Go&area=both\">NHS Workforce Statistics, NHS Digital<\/a>"}