{"_comment" : "Created by NCODowd on 27\/07\/2016 12:15:57 using v2.7","import_id" : "QIAAN59-QIAAN49-1","title" : "Have the perceptions of people feeling involved in their inpatient care changed?","analysis_commentary" : "<P>The proportion of people who definitely feel they have been involved in decisions about their care and treatment has increased from 53% in 2005 to 60% in 2015. The proportion who felt they had not been involved decreased slightly to 9% in 2015 from 11% ten years earlier.  <br><br>Updated August 2016.<\/P>","data_download_url" : {"url" : "","title" : ""},"data_source" : "<a href=\"http:\/\/www.cqc.org.uk\/content\/adult-inpatient-survey-2015\">Care Quality Commission, Adult Inpatient Survey 2015<\/a>"}