{"_comment" : "Created by EFisher on 12\/10\/2015 14:32:05 using v2.7","import_id" : "QIAAN113-2","title" : "How have the number of maternities changed over time?","analysis_commentary" : "<P>The absolute number of maternities where it is known that the woman is a smoker at time of birth has also been decreasing. In 2014\/15 a bit less than 71,000 women were known to be smokers, a decrease of 20,000 since 2006\/07. However, the total number of maternities has also been decreasing since 2011\/12 and the number and the proportion of women where smoking status is not known has increased compared to 2013\/14.  <\/P>","data_download_url" : {"url" : "","title" : ""},"data_source" : "Health & Social Care Information Centre, Women's Smoking Status at Time of Delivery"}