{"_comment" : "Created by EFisher on 20\/12\/2017 15:35:28 using v2.7","import_id" : "QIAAN82-3","title" : "What proportion of ambulance calls re-contact 999 within 24 hours?","analysis_commentary" : "<P>We saw that one in ten cases of emergency calls receive telephone only advice and that a third of patients that are seen at the scene are treated and discharged without going to hospital. A marker of how successful these different methods are is to look at how many of thee people re-contact 999 within the next 24 hours.<br><br> In 2011, there was a sizable difference between the re-contact rates for those who called 999 and didn't go to hospital depending if they were given telephone only advice or they were treated and discharged at the scene, with more people receiving telephone only advice re-contacted 999 within 24 hours. However, this gap has decreased over time, due to a reduction in the number of people re-contacting when given telephone only advise. This decline is positive and suggests that the ambulance service has improving it's ability to care when not providing face-face responses.<br><br>Updated November 2017<\/P>","data_download_url" : {"url" : "","title" : ""},"data_source" : "<a href=\"https:\/\/www.england.nhs.uk\/statistics\/statistical-work-areas\/ambulance-quality-indicators\/\">NHS England, Ambulance Quality Indicators<\/a>"}