{"_comment" : "Created by EFisher on 26\/03\/2014 17:20:27 using v2.1","import_id" : "QIAAN121-2","title" : "Did people feel their views were taken into account?","analysis_commentary" : "<P>The proportion of people who didn’t feel they had their views taken into account hasn't changed by much over the years (from 4% in 2010 to 5% in 2013), the proportion feeling they had definitely had their views taken into account has decreased from 75% in 2010 to 72% in 2013. <\/P>","data_download_url" : {"url" : "","title" : ""},"data_source" : "Care Quality Commission, Community Mental Health Survey"}