{"_comment" : "Created by EFisher on 03\/12\/2015 13:06:37 using v2.7","import_id" : "QIAAN62-2","title" : "What proportion of people feel their service makes them feel safe?","analysis_commentary" : "<P><a href=\"https:\/\/www.gov.uk\/government\/publications\/caring-for-our-future-reforming-care-and-support\">The Care and Support White Paper<\/a> states that a high-quality service must be one which keeps people safe from harm and it is important that vulnerable groups feel safety from the services social care provides. Service users were asked if they were helped to feel safe specifically by their care and support services. The proportion in 2014-15 is high with almost 85%. Again, the changes to the methodology create a break in the time series in 2014-2015 and comparison to previous years is not possible. <\/P>","data_download_url" : {"url" : "","title" : ""},"data_source" : "<a href=\"http:\/\/www.hscic.gov.uk\/article\/2021\/Website-Search?productid=18966&q=Personal+Social+Services+Adult+Social+Care+Survey%2c+England&sort=Relevance&size=10&page=1&area=both#top\">Health & Social Care Information Centre, Personal Adult Social Care Survey<\/a>"}